tidfit/__init__.py
tidfit/fit.py
tidfit-0.3.2.dist-info/METADATA
tidfit-0.3.2.dist-info/WHEEL
tidfit-0.3.2.dist-info/top_level.txt
tidfit-0.3.2.dist-info/RECORD
